dmtapi/__init__.py
dmtapi/constant.py
dmtapi/core.py
dmtapi/date_funcs.py
dmtapi/req.py
dmtapi/models/account_model.py
dmtapi/models/deal_model.py
dmtapi/models/order_model.py
dmtapi/models/position_model.py
dmtapi/models/symbol_model.py
dmtapi/models/trade_model.py
dmtapi-2025.2.dist-info/METADATA
dmtapi-2025.2.dist-info/WHEEL
dmtapi-2025.2.dist-info/top_level.txt
dmtapi-2025.2.dist-info/RECORD
