Metadata-Version: 2.2
Name: dmtapi
Version: 2025.2
Summary: Dynamo MetaTrader API
Author-email: "Hamim (Dynamo)" <developer@dynamotrader.com>
License: MIT
Project-URL: Homepage, https://github.com/dynamotrader/dmtapi
Project-URL: Repository, https://github.com/dynamotrader/dmtapi.git
Keywords: metatrader,trading,api,mt4,mt5,forex
Classifier: Intended Audience :: Developers
Classifier: Programming Language :: Python :: 3.9
Classifier: Programming Language :: Python :: 3.10
Classifier: Programming Language :: Python :: 3.11
Classifier: Programming Language :: Python :: 3.12
Requires-Python: >=3.9
Requires-Dist: httpx>=0.28.1
Requires-Dist: pendulum>=3.0.0
Requires-Dist: pydantic>=2.10.6
Requires-Dist: pytz>=2024.1
Provides-Extra: dev
Requires-Dist: pytest>=8.3.4; extra == "dev"
Requires-Dist: pytest-asyncio>=0.25.3; extra == "dev"
Requires-Dist: mypy>=1.15.0; extra == "dev"
Requires-Dist: ruff>=0.3.0; extra == "dev"
Requires-Dist: black>=24.2.0; extra == "dev"
Requires-Dist: coverage>=7.4.0; extra == "dev"
Requires-Dist: pre-commit>=3.6.0; extra == "dev"
